{
  "ComponentIndexes": {},
  "ControlUniqueGuids": {},
  "ControlUniqueIds": {
    "Activity initiated_Column1": 158,
    "ALT MODEL_DataCard1": 44,
    "ALT MODEL_DataCard2": 250,
    "ALTERNATOR MAKE_DataCard1": 24,
    "ALTERNATOR MAKE_DataCard2": 238,
    "ALTERNATOR S.NO:_DataCard1": 29,
    "ALTERNATOR S.NO:_DataCard2": 241,
    "App": 1,
    "Asset List": 186,
    "Assigned To_Column1": 156,
    "Attended Date_DataCard1": 300,
    "Body1": 466,
    "Border Color Palatte": 490,
    "Brand and Grade of Lube oil_DataCard1": 440,
    "Breakdown Issues_DataCard1": 327,
    "Button1": 477,
    "Button2": 474,
    "Button3": 133,
    "Button3_10": 339,
    "Button3_11": 338,
    "Button3_12": 383,
    "Button3_13": 382,
    "Button3_6": 307,
    "Button3_7": 306,
    "Button3_8": 452,
    "Button3_9": 451,
    "Button4": 315,
    "Button6": 486,
    "Button6_1": 487,
    "Button6_2": 485,
    "Button6_3": 488,
    "Button6_4": 484,
    "Button6_5": 483,
    "Button7": 225,
    "Call Log Date_Column1": 143,
    "Call Log Type_Column1": 152,
    "Capacity(Kva)_DataCard1": 103,
    "CAPACITY_DataCard1": 34,
    "CAPACITY_DataCard2": 244,
    "ComboBox1": 263,
    "ComboBox2": 459,
    "ComboBox3": 75,
    "ComboBox4": 174,
    "ComboBox5": 173,
    "Complaint_DataCard2": 108,
    "Contact Person Designation_DataCard1": 295,
    "Contact Person Email ID_DataCard1": 290,
    "Contact Person Mobile No_DataCard1": 285,
    "Contact Person Name_DataCard1": 280,
    "Contract Person_Column1": 159,
    "Contract Person_DataCard1": 128,
    "Controller Type_DataCard1": 415,
    "Cumulative Hours_DataCard1": 430,
    "Cust Email Id_DataCard1": 209,
    "Cust Phone Number_DataCard1": 214,
    "Customer Address_DataCard1": 204,
    "Customer City_DataCard1": 199,
    "Customer Company Name_Column1": 146,
    "Customer Company Name_DataCard1": 260,
    "Customer Company Name_DataCard2": 78,
    "Customer Location_Column1": 147,
    "Customer Location_DataCard1": 275,
    "Customer Location_DataCard3": 83,
    "Customer Mail Id_Column1": 155,
    "Customer Name_DataCard1": 194,
    "Customer Number_Column1": 148,
    "Customer Number_DataCard2": 88,
    "DataCard1": 450,
    "DataCard2": 337,
    "DataCard3": 381,
    "DataCard4": 305,
    "DataCard5": 224,
    "DataCard6": 49,
    "DataCardKey1": 267,
    "DataCardKey10": 392,
    "DataCardKey11": 407,
    "DataCardKey12": 412,
    "DataCardKey13": 417,
    "DataCardKey14": 422,
    "DataCardKey15": 427,
    "DataCardKey16": 432,
    "DataCardKey17": 437,
    "DataCardKey18": 442,
    "DataCardKey19": 447,
    "DataCardKey2": 272,
    "DataCardKey20": 387,
    "DataCardKey21": 292,
    "DataCardKey22": 319,
    "DataCardKey23": 324,
    "DataCardKey24": 329,
    "DataCardKey25": 334,
    "DataCardKey26": 343,
    "DataCardKey27": 348,
    "DataCardKey28": 353,
    "DataCardKey29": 358,
    "DataCardKey3": 262,
    "DataCardKey30": 363,
    "DataCardKey31": 368,
    "DataCardKey32": 373,
    "DataCardKey33": 378,
    "DataCardKey34": 282,
    "DataCardKey35": 125,
    "DataCardKey36": 105,
    "DataCardKey37": 100,
    "DataCardKey38": 69,
    "DataCardKey39": 115,
    "DataCardKey4": 277,
    "DataCardKey40": 130,
    "DataCardKey41": 11,
    "DataCardKey42": 16,
    "DataCardKey43": 21,
    "DataCardKey44": 26,
    "DataCardKey45": 31,
    "DataCardKey46": 36,
    "DataCardKey47": 41,
    "DataCardKey48": 46,
    "DataCardKey49": 230,
    "DataCardKey5": 302,
    "DataCardKey50": 233,
    "DataCardKey51": 236,
    "DataCardKey52": 58,
    "DataCardKey53": 64,
    "DataCardKey54": 222,
    "DataCardKey55": 85,
    "DataCardKey56": 90,
    "DataCardKey57": 110,
    "DataCardKey58": 120,
    "DataCardKey59": 79,
    "DataCardKey6": 402,
    "DataCardKey60": 74,
    "DataCardKey61": 95,
    "DataCardKey62": 239,
    "DataCardKey63": 242,
    "DataCardKey64": 245,
    "DataCardKey65": 248,
    "DataCardKey66": 251,
    "DataCardKey7": 297,
    "DataCardKey75": 197,
    "DataCardKey76": 207,
    "DataCardKey77": 212,
    "DataCardKey78": 216,
    "DataCardKey79": 202,
    "DataCardKey8": 287,
    "DataCardKey9": 397,
    "DataCardValue1": 268,
    "DataCardValue10": 393,
    "DataCardValue11": 408,
    "DataCardValue12": 413,
    "DataCardValue13": 418,
    "DataCardValue14": 423,
    "DataCardValue15": 428,
    "DataCardValue16": 433,
    "DataCardValue17": 438,
    "DataCardValue18": 443,
    "DataCardValue19": 448,
    "DataCardValue2": 273,
    "DataCardValue20": 388,
    "DataCardValue21": 293,
    "DataCardValue22": 320,
    "DataCardValue23": 325,
    "DataCardValue24": 330,
    "DataCardValue25": 335,
    "DataCardValue26": 344,
    "DataCardValue27": 349,
    "DataCardValue28": 354,
    "DataCardValue29": 359,
    "DataCardValue3": 303,
    "DataCardValue30": 364,
    "DataCardValue31": 369,
    "DataCardValue32": 374,
    "DataCardValue33": 126,
    "DataCardValue34": 106,
    "DataCardValue35": 101,
    "DataCardValue36": 70,
    "DataCardValue37": 116,
    "DataCardValue38": 131,
    "DataCardValue39": 12,
    "DataCardValue4": 278,
    "DataCardValue40": 17,
    "DataCardValue41": 22,
    "DataCardValue42": 27,
    "DataCardValue43": 32,
    "DataCardValue44": 37,
    "DataCardValue45": 42,
    "DataCardValue46": 47,
    "DataCardValue47": 231,
    "DataCardValue48": 234,
    "DataCardValue49": 237,
    "DataCardValue5": 283,
    "DataCardValue50": 240,
    "DataCardValue51": 60,
    "DataCardValue52": 65,
    "DataCardValue53": 220,
    "DataCardValue54": 86,
    "DataCardValue55": 91,
    "DataCardValue56": 111,
    "DataCardValue57": 121,
    "DataCardValue58": 80,
    "DataCardValue59": 76,
    "DataCardValue6": 298,
    "DataCardValue60": 96,
    "DataCardValue61": 243,
    "DataCardValue62": 246,
    "DataCardValue63": 249,
    "DataCardValue64": 252,
    "DataCardValue7": 288,
    "DataCardValue73": 195,
    "DataCardValue74": 205,
    "DataCardValue75": 210,
    "DataCardValue76": 217,
    "DataCardValue77": 200,
    "DataCardValue8": 403,
    "DataCardValue9": 398,
    "DataTable1": 141,
    "Description of Work Done_DataCard1": 332,
    "DG Set_DataCard1": 410,
    "Digital Signature_DataCard1": 376,
    "Dropdown1": 139,
    "EDIT_ASSET_LIST": 188,
    "ENG MODEL_DataCard1": 39,
    "ENG MODEL_DataCard2": 247,
    "ENGINE MAKE_DataCard1": 14,
    "ENGINE MAKE_DataCard2": 232,
    "Engine Model_DataCard1": 390,
    "Engine No_Column1": 150,
    "Engine No_DataCard1": 98,
    "Engine Serial No_DataCard2": 385,
    "ENGINE SR.NO:_DataCard1": 19,
    "ENGINE SR.NO:_DataCard2": 235,
    "EQMNT NO:_DataCard1": 9,
    "EQMNT NO:_DataCard2": 229,
    "Eqmnt No_Column1": 145,
    "Equipment Name_Column1": 149,
    "Equipment Name_DataCard1": 93,
    "Equipment No_DataCard1": 395,
    "Equipment Type_Column1": 144,
    "Equipment Type_DataCard1": 400,
    "Equipment Type_DataCard2": 67,
    "ErrorMessage1": 269,
    "ErrorMessage10": 394,
    "ErrorMessage11": 409,
    "ErrorMessage12": 414,
    "ErrorMessage13": 419,
    "ErrorMessage14": 424,
    "ErrorMessage15": 429,
    "ErrorMessage16": 434,
    "ErrorMessage17": 439,
    "ErrorMessage18": 444,
    "ErrorMessage19": 449,
    "ErrorMessage2": 274,
    "ErrorMessage20": 389,
    "ErrorMessage21": 294,
    "ErrorMessage22": 321,
    "ErrorMessage23": 326,
    "ErrorMessage24": 331,
    "ErrorMessage25": 336,
    "ErrorMessage26": 345,
    "ErrorMessage27": 350,
    "ErrorMessage28": 355,
    "ErrorMessage29": 360,
    "ErrorMessage3": 264,
    "ErrorMessage30": 365,
    "ErrorMessage31": 370,
    "ErrorMessage32": 375,
    "ErrorMessage33": 380,
    "ErrorMessage34": 284,
    "ErrorMessage35": 127,
    "ErrorMessage36": 107,
    "ErrorMessage37": 102,
    "ErrorMessage38": 71,
    "ErrorMessage39": 117,
    "ErrorMessage4": 279,
    "ErrorMessage40": 132,
    "ErrorMessage41": 13,
    "ErrorMessage42": 18,
    "ErrorMessage43": 23,
    "ErrorMessage44": 28,
    "ErrorMessage45": 33,
    "ErrorMessage46": 38,
    "ErrorMessage47": 43,
    "ErrorMessage48": 48,
    "ErrorMessage49": 223,
    "ErrorMessage5": 304,
    "ErrorMessage50": 81,
    "ErrorMessage52": 61,
    "ErrorMessage53": 66,
    "ErrorMessage55": 87,
    "ErrorMessage56": 92,
    "ErrorMessage57": 112,
    "ErrorMessage58": 122,
    "ErrorMessage6": 404,
    "ErrorMessage60": 77,
    "ErrorMessage61": 97,
    "ErrorMessage7": 299,
    "ErrorMessage75": 198,
    "ErrorMessage76": 208,
    "ErrorMessage77": 213,
    "ErrorMessage78": 218,
    "ErrorMessage79": 203,
    "ErrorMessage8": 289,
    "ErrorMessage9": 399,
    "Fab No_DataCard1": 72,
    "Failed at Hours (HMR)_DataCard1": 425,
    "Failed On Date_DataCard1": 420,
    "Form1": 55,
    "Form2": 8,
    "frmAssetDetails": 384,
    "frmEditAssetList": 193,
    "frmIssueDetails": 316,
    "frmPerformanceCheck": 340,
    "frmSrDetails": 259,
    "frmViewAssetList": 228,
    "FSR_FORM_1": 254,
    "FSR_FORM_2": 309,
    "FSR_TRACKER": 453,
    "Full load AMPS_DataCard1": 356,
    "Full load KW_DataCard1": 361,
    "galAssetList": 175,
    "Gallery1": 313,
    "Gallery2": 460,
    "galleryTemplate1": 314,
    "galleryTemplate2": 461,
    "galleryTemplate3": 176,
    "Group1": 308,
    "Group1_1": 468,
    "Group1_2": 185,
    "Group1_3": 253,
    "Group1_4": 489,
    "Group1_5": 50,
    "HOME_SCREEN": 469,
    "Icon1": 161,
    "Icon10": 227,
    "Icon2": 471,
    "Icon3": 475,
    "Icon4": 256,
    "Icon4_1": 311,
    "Icon4_2": 53,
    "Icon4_3": 455,
    "Icon4_4": 167,
    "Icon4_5": 190,
    "Icon4_6": 481,
    "Icon4_7": 5,
    "Icon5": 258,
    "Icon5_1": 54,
    "Icon5_2": 457,
    "Icon5_3": 169,
    "Icon5_4": 192,
    "Icon5_5": 7,
    "Icon6": 170,
    "Icon7": 137,
    "Icon8": 138,
    "iconCheck1": 163,
    "iconCircle1": 162,
    "Image2": 480,
    "Image3": 476,
    "Label1": 52,
    "Label10": 226,
    "Label2": 257,
    "Label2_1": 312,
    "Label2_2": 456,
    "Label2_3": 168,
    "Label2_4": 191,
    "Label2_5": 482,
    "Label2_6": 6,
    "Label3": 59,
    "Label4": 463,
    "Label5": 136,
    "Label6": 140,
    "Label7": 470,
    "Label8": 187,
    "Label9": 180,
    "Last B Check at HMR_DataCard1": 435,
    "LblSuccessMsg1": 164,
    "Lube Pressure_DataCard1": 351,
    "Lube Temp_DataCard1": 346,
    "Main Color": 491,
    "Menu Screen": 478,
    "Mode of Transport_DataCard1": 371,
    "NEW_ASSET_LIST": 3,
    "NextArrow2": 465,
    "NextArrow3": 181,
    "OEM (Make)_DataCard1": 405,
    "PenInput1": 379,
    "Primary Color": 492,
    "Priority_Column1": 154,
    "Priority_DataCard2": 118,
    "Product_Column1": 151,
    "Rectangle1": 255,
    "Rectangle1_1": 310,
    "Rectangle1_2": 454,
    "Rectangle1_3": 166,
    "Rectangle1_4": 189,
    "Rectangle1_5": 479,
    "Rectangle1_6": 4,
    "Rectangle2": 135,
    "Remarks_Column1": 153,
    "Remarks_DataCard1": 113,
    "secondary Color": 493,
    "Separator2": 467,
    "Separator3": 184,
    "Service Breakdown Type_DataCard1": 322,
    "Service Creation": 51,
    "Service list": 134,
    "Service Representative Name_DataCard1": 366,
    "Service Request Action_DataCard1": 123,
    "Service Request Type_DataCard1": 317,
    "SR Date_DataCard1": 270,
    "SR Date_DataCard3": 62,
    "SR Status_Column1": 157,
    "StarVisible1": 266,
    "StarVisible10": 391,
    "StarVisible11": 406,
    "StarVisible12": 411,
    "StarVisible13": 416,
    "StarVisible14": 421,
    "StarVisible15": 426,
    "StarVisible16": 431,
    "StarVisible17": 436,
    "StarVisible18": 441,
    "StarVisible19": 446,
    "StarVisible2": 271,
    "StarVisible20": 386,
    "StarVisible21": 291,
    "StarVisible22": 318,
    "StarVisible23": 323,
    "StarVisible24": 328,
    "StarVisible25": 333,
    "StarVisible26": 342,
    "StarVisible27": 347,
    "StarVisible28": 352,
    "StarVisible29": 357,
    "StarVisible3": 261,
    "StarVisible30": 362,
    "StarVisible31": 367,
    "StarVisible32": 372,
    "StarVisible33": 377,
    "StarVisible34": 281,
    "StarVisible35": 124,
    "StarVisible36": 104,
    "StarVisible37": 99,
    "StarVisible38": 68,
    "StarVisible39": 114,
    "StarVisible4": 276,
    "StarVisible40": 129,
    "StarVisible41": 10,
    "StarVisible42": 15,
    "StarVisible43": 20,
    "StarVisible44": 25,
    "StarVisible45": 30,
    "StarVisible46": 35,
    "StarVisible47": 40,
    "StarVisible48": 45,
    "StarVisible49": 221,
    "StarVisible5": 301,
    "StarVisible50": 82,
    "StarVisible52": 57,
    "StarVisible53": 63,
    "StarVisible55": 84,
    "StarVisible56": 89,
    "StarVisible57": 109,
    "StarVisible58": 119,
    "StarVisible6": 401,
    "StarVisible60": 73,
    "StarVisible61": 94,
    "StarVisible7": 296,
    "StarVisible75": 196,
    "StarVisible76": 206,
    "StarVisible77": 211,
    "StarVisible78": 215,
    "StarVisible79": 201,
    "StarVisible8": 286,
    "StarVisible9": 396,
    "Status_DataCard1": 219,
    "Subtitle2": 464,
    "Subtitle3": 178,
    "Subtitle3_1": 182,
    "Subtitle3_2": 179,
    "Subtitle3_3": 183,
    "SUCCESS_SCREEN": 160,
    "TextInput1": 472,
    "TextInput1_1": 473,
    "TextInput2": 171,
    "TextInput2_1": 172,
    "TextInput3": 458,
    "Third Color": 494,
    "Title_Column1": 142,
    "Title_DataCard1": 265,
    "Title_DataCard3": 56,
    "Title2": 462,
    "Title3": 177,
    "Type of Coolant_DataCard1": 445,
    "VIEW_ASSET_LIST": 165,
    "Water Temp_DataCard1": 341
  },
  "FunctionParamsInvariantScripts": {},
  "FunctionParamsInvariantScriptsOnInstances": {},
  "HeaderLastSavedDateTimeUTC": "01/25/2023 09:05:02",
  "IsLegacyComponentAllowGlobalScopeCase": false,
  "LocalConnectionIDReferences": {
    "71e95593-2791-4577-94bb-f451d9939c3c": "\"/providers/microsoft.powerapps/apis/shared_sharepointonline/connections/c69eda498a0f43e8a2fdb022fb2691f8\""
  },
  "LocalDatabaseReferencesAsEmpty": false,
  "LocalResourceFileNames": {
    "997194": "0001.jpg",
    "App1": "0002.jpg",
    "App2": "0003.jpg",
    "App4": "0004.jpg",
    "App8": "0005.jpeg",
    "background": "0006.jpg",
    "Home Screen Image": "0007.jpeg",
    "Login": "0008.jpg",
    "Logout": "0009.jpeg",
    "Service Request": "0010.jpg",
    "Submit": "0011.jpg",
    "Technology-modern-abstract-background-vector": "0012.jpg",
    "white-gradient-blue-linear-1536x2048-c2-87cefa-ffffff-a-90-f-14": "0013.png"
  },
  "LocalResourceRootPaths": {
    "997194": "https://docserverpwaprodsin.blob.core.windows.net/a1f89309-1cc2-41bb-b664-de17618b439b-1/resource/Assets0Images00001.jpg?sv=2017-04-17&sr=b&sig=LBQ%2Bhhb%2FtMmebJ4kov3Cisn8ibKjbgrShTrDuoZDcAM%3D&spr=https&se=2023-01-26T09%3A03%3A25Z&sp=r",
    "App1": "https://docserverpwaprodsin.blob.core.windows.net/a1f89309-1cc2-41bb-b664-de17618b439b-1/resource/Assets0Images00002.jpg?sv=2017-04-17&sr=b&sig=%2BsThHgfsgMIlk%2BIBza0njWp0l7nKxrb06PVJUBj3ZkI%3D&spr=https&se=2023-01-26T09%3A03%3A25Z&sp=r",
    "App2": "https://docserverpwaprodsin.blob.core.windows.net/a1f89309-1cc2-41bb-b664-de17618b439b-1/resource/Assets0Images00003.jpg?sv=2017-04-17&sr=b&sig=s7umDuI6Vubn06bkQbD1vNVf%2Fr4GCBjhv2nLt%2FMS5U8%3D&spr=https&se=2023-01-26T09%3A03%3A25Z&sp=r",
    "App4": "https://docserverpwaprodsin.blob.core.windows.net/a1f89309-1cc2-41bb-b664-de17618b439b-1/resource/Assets0Images00004.jpg?sv=2017-04-17&sr=b&sig=MzLUJ2HzIHmb7BkQZ9vMdv6ZgUUjTToWtJMa9eQoVTw%3D&spr=https&se=2023-01-26T09%3A03%3A25Z&sp=r",
    "App8": "https://docserverpwaprodsin.blob.core.windows.net/a1f89309-1cc2-41bb-b664-de17618b439b-1/resource/Assets0Images00005.jpeg?sv=2017-04-17&sr=b&sig=f1vM2ADweRjsJ%2F6DCjc4lX7a7zowAyBf4V4qcBfhIeM%3D&spr=https&se=2023-01-26T09%3A03%3A25Z&sp=r",
    "background": "https://docserverpwaprodsin.blob.core.windows.net/a1f89309-1cc2-41bb-b664-de17618b439b-1/resource/Assets0Images00006.jpg?sv=2017-04-17&sr=b&sig=q9yNcBcEY09m49Y3LkKiUJxf2V0bEblGMKHIdXOCZWM%3D&spr=https&se=2023-01-26T09%3A03%3A25Z&sp=r",
    "Home Screen Image": "https://docserverpwaprodsin.blob.core.windows.net/a1f89309-1cc2-41bb-b664-de17618b439b-1/resource/Assets0Images00007.jpeg?sv=2017-04-17&sr=b&sig=HkzDNtZ74D5THnXCYNaF6QlyBhVK9IYJeKR4iDbSpUY%3D&spr=https&se=2023-01-26T09%3A03%3A25Z&sp=r",
    "Login": "https://docserverpwaprodsin.blob.core.windows.net/a1f89309-1cc2-41bb-b664-de17618b439b-1/resource/Assets0Images00008.jpg?sv=2017-04-17&sr=b&sig=cRawtYCMMY3WrWTNPhruAqAvApzgaHa0%2BHIuSLwHjTU%3D&spr=https&se=2023-01-26T09%3A03%3A25Z&sp=r",
    "Logout": "https://docserverpwaprodsin.blob.core.windows.net/a1f89309-1cc2-41bb-b664-de17618b439b-1/resource/Assets0Images00009.jpeg?sv=2017-04-17&sr=b&sig=MWoJkXWohF5JBdYgDWeRevZrOQ88D5AXNcOrDWq%2Bt5s%3D&spr=https&se=2023-01-26T09%3A03%3A25Z&sp=r",
    "Service Request": "https://docserverpwaprodsin.blob.core.windows.net/a1f89309-1cc2-41bb-b664-de17618b439b-1/resource/Assets0Images00010.jpg?sv=2017-04-17&sr=b&sig=MbL%2FPysv4mlP8vg1B%2B0bPpGxws%2B9D%2Fab2j0quvrV%2Bm8%3D&spr=https&se=2023-01-26T09%3A03%3A25Z&sp=r",
    "Submit": "https://docserverpwaprodsin.blob.core.windows.net/a1f89309-1cc2-41bb-b664-de17618b439b-1/resource/Assets0Images00011.jpg?sv=2017-04-17&sr=b&sig=KT87Djin52TNN85YV7KqpswFS259vIYrB3tI6Stmm6Y%3D&spr=https&se=2023-01-26T09%3A03%3A25Z&sp=r",
    "Technology-modern-abstract-background-vector": "https://docserverpwaprodsin.blob.core.windows.net/a1f89309-1cc2-41bb-b664-de17618b439b-1/resource/Assets0Images00012.jpg?sv=2017-04-17&sr=b&sig=t7OTDFqaSKU7CdZzmGr2nK7CzYtaCpcZuknaHUk%2FQtU%3D&spr=https&se=2023-01-26T09%3A03%3A25Z&sp=r",
    "white-gradient-blue-linear-1536x2048-c2-87cefa-ffffff-a-90-f-14": "https://docserverpwaprodsin.blob.core.windows.net/a1f89309-1cc2-41bb-b664-de17618b439b-1/resource/Assets0Images00013.png?sv=2017-04-17&sr=b&sig=eawad3Exx3BtIdx%2F1Wy1OnSbKsMdWHjw%2BeqviM50sHQ%3D&spr=https&se=2023-01-26T09%3A03%3A25Z&sp=r"
  },
  "OrderComponentMetadata": {},
  "OrderComponentTemplate": {},
  "OrderDataSource": {
    "Asset List_1": 0,
    "Call Status Dropdown": 1,
    "Call Type Dropdown": 2,
    "Client List DB-": 3,
    "ColViews": 10,
    "ComboBoxSample": 4,
    "CustomGallerySample": 5,
    "DropDownSample": 6,
    "FSR _Form": 7,
    "LoginDB": 8,
    "Manual Service Creation": 9
  },
  "OrderGroupControls": {
    "Group1": {
      "Icon4": 2,
      "Icon5": 3,
      "Label2": 1,
      "Rectangle1": 0
    },
    "Group1_1": {
      "Icon4_3": 2,
      "Icon5_2": 3,
      "Label2_2": 1,
      "Rectangle1_2": 0
    },
    "Group1_2": {
      "Icon4_4": 2,
      "Icon5_3": 3,
      "Label2_3": 1,
      "Rectangle1_3": 0
    },
    "Group1_3": {
      "Icon4_5": 2,
      "Icon5_4": 3,
      "Label2_4": 1,
      "Rectangle1_4": 0
    },
    "Group1_4": {
      "Icon4_6": 2,
      "Label2_5": 1,
      "Rectangle1_5": 0
    },
    "Group1_5": {
      "Icon4_7": 2,
      "Icon5_5": 3,
      "Label2_6": 1,
      "Rectangle1_6": 0
    }
  },
  "OrderPcfTemplate": {},
  "OrderTemplate": {},
  "OrderXMLTemplate": {
    "button": 7,
    "circle": 9,
    "combobox": 6,
    "datepicker": 5,
    "dropdown": 8,
    "form": 3,
    "gallery": 10,
    "icon": 1,
    "image": 12,
    "inkControl": 11,
    "label": 2,
    "rectangle": 0,
    "text": 4
  },
  "OverridablePropertiesEntry": {
    "Activity initiated_Column1": {},
    "ALT MODEL_DataCard1": {},
    "ALT MODEL_DataCard2": {},
    "ALTERNATOR MAKE_DataCard1": {},
    "ALTERNATOR MAKE_DataCard2": {},
    "ALTERNATOR S.NO:_DataCard1": {},
    "ALTERNATOR S.NO:_DataCard2": {},
    "App": {},
    "Asset List": {},
    "Assigned To_Column1": {},
    "Attended Date_DataCard1": {},
    "Body1": {},
    "Border Color Palatte": {},
    "Brand and Grade of Lube oil_DataCard1": {},
    "Breakdown Issues_DataCard1": {},
    "Button1": {},
    "Button2": {},
    "Button3": {},
    "Button3_10": {},
    "Button3_11": {},
    "Button3_12": {},
    "Button3_13": {},
    "Button3_6": {},
    "Button3_7": {},
    "Button3_8": {},
    "Button3_9": {},
    "Button4": {},
    "Button6": {},
    "Button6_1": {},
    "Button6_2": {},
    "Button6_3": {},
    "Button6_4": {},
    "Button6_5": {},
    "Button7": {},
    "Call Log Date_Column1": {},
    "Call Log Type_Column1": {},
    "Capacity(Kva)_DataCard1": {},
    "CAPACITY_DataCard1": {},
    "CAPACITY_DataCard2": {},
    "ComboBox1": {},
    "ComboBox2": {},
    "ComboBox3": {},
    "ComboBox4": {},
    "ComboBox5": {},
    "Complaint_DataCard2": {},
    "Contact Person Designation_DataCard1": {},
    "Contact Person Email ID_DataCard1": {},
    "Contact Person Mobile No_DataCard1": {},
    "Contact Person Name_DataCard1": {},
    "Contract Person_Column1": {},
    "Contract Person_DataCard1": {},
    "Controller Type_DataCard1": {},
    "Cumulative Hours_DataCard1": {},
    "Cust Email Id_DataCard1": {},
    "Cust Phone Number_DataCard1": {},
    "Customer Address_DataCard1": {},
    "Customer City_DataCard1": {},
    "Customer Company Name_Column1": {},
    "Customer Company Name_DataCard1": {},
    "Customer Company Name_DataCard2": {},
    "Customer Location_Column1": {},
    "Customer Location_DataCard1": {},
    "Customer Location_DataCard3": {},
    "Customer Mail Id_Column1": {},
    "Customer Name_DataCard1": {},
    "Customer Number_Column1": {},
    "Customer Number_DataCard2": {},
    "DataCard1": {},
    "DataCard2": {},
    "DataCard3": {},
    "DataCard4": {},
    "DataCard5": {},
    "DataCard6": {},
    "DataCardKey1": {},
    "DataCardKey10": {},
    "DataCardKey11": {},
    "DataCardKey12": {},
    "DataCardKey13": {},
    "DataCardKey14": {},
    "DataCardKey15": {},
    "DataCardKey16": {},
    "DataCardKey17": {},
    "DataCardKey18": {},
    "DataCardKey19": {},
    "DataCardKey2": {},
    "DataCardKey20": {},
    "DataCardKey21": {},
    "DataCardKey22": {},
    "DataCardKey23": {},
    "DataCardKey24": {},
    "DataCardKey25": {},
    "DataCardKey26": {},
    "DataCardKey27": {},
    "DataCardKey28": {},
    "DataCardKey29": {},
    "DataCardKey3": {},
    "DataCardKey30": {},
    "DataCardKey31": {},
    "DataCardKey32": {},
    "DataCardKey33": {},
    "DataCardKey34": {},
    "DataCardKey35": {},
    "DataCardKey36": {},
    "DataCardKey37": {},
    "DataCardKey38": {},
    "DataCardKey39": {},
    "DataCardKey4": {},
    "DataCardKey40": {},
    "DataCardKey41": {},
    "DataCardKey42": {},
    "DataCardKey43": {},
    "DataCardKey44": {},
    "DataCardKey45": {},
    "DataCardKey46": {},
    "DataCardKey47": {},
    "DataCardKey48": {},
    "DataCardKey49": {},
    "DataCardKey5": {},
    "DataCardKey50": {},
    "DataCardKey51": {},
    "DataCardKey52": {},
    "DataCardKey53": {},
    "DataCardKey54": {},
    "DataCardKey55": {},
    "DataCardKey56": {},
    "DataCardKey57": {},
    "DataCardKey58": {},
    "DataCardKey59": {},
    "DataCardKey6": {},
    "DataCardKey60": {},
    "DataCardKey61": {},
    "DataCardKey62": {},
    "DataCardKey63": {},
    "DataCardKey64": {},
    "DataCardKey65": {},
    "DataCardKey66": {},
    "DataCardKey7": {},
    "DataCardKey75": {},
    "DataCardKey76": {},
    "DataCardKey77": {},
    "DataCardKey78": {},
    "DataCardKey79": {},
    "DataCardKey8": {},
    "DataCardKey9": {},
    "DataCardValue1": {},
    "DataCardValue10": {},
    "DataCardValue11": {},
    "DataCardValue12": {},
    "DataCardValue13": {},
    "DataCardValue14": {},
    "DataCardValue15": {},
    "DataCardValue16": {},
    "DataCardValue17": {},
    "DataCardValue18": {},
    "DataCardValue19": {},
    "DataCardValue2": {},
    "DataCardValue20": {},
    "DataCardValue21": {},
    "DataCardValue22": {},
    "DataCardValue23": {},
    "DataCardValue24": {},
    "DataCardValue25": {},
    "DataCardValue26": {},
    "DataCardValue27": {},
    "DataCardValue28": {},
    "DataCardValue29": {},
    "DataCardValue3": {},
    "DataCardValue30": {},
    "DataCardValue31": {},
    "DataCardValue32": {},
    "DataCardValue33": {},
    "DataCardValue34": {},
    "DataCardValue35": {},
    "DataCardValue36": {},
    "DataCardValue37": {},
    "DataCardValue38": {},
    "DataCardValue39": {},
    "DataCardValue4": {},
    "DataCardValue40": {},
    "DataCardValue41": {},
    "DataCardValue42": {},
    "DataCardValue43": {},
    "DataCardValue44": {},
    "DataCardValue45": {},
    "DataCardValue46": {},
    "DataCardValue47": {},
    "DataCardValue48": {},
    "DataCardValue49": {},
    "DataCardValue5": {},
    "DataCardValue50": {},
    "DataCardValue51": {},
    "DataCardValue52": {},
    "DataCardValue53": {},
    "DataCardValue54": {},
    "DataCardValue55": {},
    "DataCardValue56": {},
    "DataCardValue57": {},
    "DataCardValue58": {},
    "DataCardValue59": {},
    "DataCardValue6": {},
    "DataCardValue60": {},
    "DataCardValue61": {},
    "DataCardValue62": {},
    "DataCardValue63": {},
    "DataCardValue64": {},
    "DataCardValue7": {},
    "DataCardValue73": {},
    "DataCardValue74": {},
    "DataCardValue75": {},
    "DataCardValue76": {},
    "DataCardValue77": {},
    "DataCardValue8": {},
    "DataCardValue9": {},
    "DataTable1": {},
    "Description of Work Done_DataCard1": {},
    "DG Set_DataCard1": {},
    "Digital Signature_DataCard1": {},
    "Dropdown1": {},
    "EDIT_ASSET_LIST": {},
    "ENG MODEL_DataCard1": {},
    "ENG MODEL_DataCard2": {},
    "ENGINE MAKE_DataCard1": {},
    "ENGINE MAKE_DataCard2": {},
    "Engine Model_DataCard1": {},
    "Engine No_Column1": {},
    "Engine No_DataCard1": {},
    "Engine Serial No_DataCard2": {},
    "ENGINE SR.NO:_DataCard1": {},
    "ENGINE SR.NO:_DataCard2": {},
    "EQMNT NO:_DataCard1": {},
    "EQMNT NO:_DataCard2": {},
    "Eqmnt No_Column1": {},
    "Equipment Name_Column1": {},
    "Equipment Name_DataCard1": {},
    "Equipment No_DataCard1": {},
    "Equipment Type_Column1": {},
    "Equipment Type_DataCard1": {},
    "Equipment Type_DataCard2": {},
    "ErrorMessage1": {},
    "ErrorMessage10": {},
    "ErrorMessage11": {},
    "ErrorMessage12": {},
    "ErrorMessage13": {},
    "ErrorMessage14": {},
    "ErrorMessage15": {},
    "ErrorMessage16": {},
    "ErrorMessage17": {},
    "ErrorMessage18": {},
    "ErrorMessage19": {},
    "ErrorMessage2": {},
    "ErrorMessage20": {},
    "ErrorMessage21": {},
    "ErrorMessage22": {},
    "ErrorMessage23": {},
    "ErrorMessage24": {},
    "ErrorMessage25": {},
    "ErrorMessage26": {},
    "ErrorMessage27": {},
    "ErrorMessage28": {},
    "ErrorMessage29": {},
    "ErrorMessage3": {},
    "ErrorMessage30": {},
    "ErrorMessage31": {},
    "ErrorMessage32": {},
    "ErrorMessage33": {},
    "ErrorMessage34": {},
    "ErrorMessage35": {},
    "ErrorMessage36": {},
    "ErrorMessage37": {},
    "ErrorMessage38": {},
    "ErrorMessage39": {},
    "ErrorMessage4": {},
    "ErrorMessage40": {},
    "ErrorMessage41": {},
    "ErrorMessage42": {},
    "ErrorMessage43": {},
    "ErrorMessage44": {},
    "ErrorMessage45": {},
    "ErrorMessage46": {},
    "ErrorMessage47": {},
    "ErrorMessage48": {},
    "ErrorMessage49": {},
    "ErrorMessage5": {},
    "ErrorMessage50": {},
    "ErrorMessage52": {},
    "ErrorMessage53": {},
    "ErrorMessage55": {},
    "ErrorMessage56": {},
    "ErrorMessage57": {},
    "ErrorMessage58": {},
    "ErrorMessage6": {},
    "ErrorMessage60": {},
    "ErrorMessage61": {},
    "ErrorMessage7": {},
    "ErrorMessage75": {},
    "ErrorMessage76": {},
    "ErrorMessage77": {},
    "ErrorMessage78": {},
    "ErrorMessage79": {},
    "ErrorMessage8": {},
    "ErrorMessage9": {},
    "Fab No_DataCard1": {},
    "Failed at Hours (HMR)_DataCard1": {},
    "Failed On Date_DataCard1": {},
    "Form1": {},
    "Form2": {},
    "frmAssetDetails": {},
    "frmEditAssetList": {},
    "frmIssueDetails": {},
    "frmPerformanceCheck": {},
    "frmSrDetails": {},
    "frmViewAssetList": {},
    "FSR_FORM_1": {},
    "FSR_FORM_2": {},
    "FSR_TRACKER": {},
    "Full load AMPS_DataCard1": {},
    "Full load KW_DataCard1": {},
    "galAssetList": {},
    "Gallery1": {},
    "Gallery2": {},
    "galleryTemplate1": {},
    "galleryTemplate2": {},
    "galleryTemplate3": {},
    "Group1": {},
    "Group1_1": {},
    "Group1_2": {},
    "Group1_3": {},
    "Group1_4": {},
    "Group1_5": {},
    "HOME_SCREEN": {},
    "Icon1": {},
    "Icon10": {},
    "Icon2": {},
    "Icon3": {},
    "Icon4": {},
    "Icon4_1": {},
    "Icon4_2": {},
    "Icon4_3": {},
    "Icon4_4": {},
    "Icon4_5": {},
    "Icon4_6": {},
    "Icon4_7": {},
    "Icon5": {},
    "Icon5_1": {},
    "Icon5_2": {},
    "Icon5_3": {},
    "Icon5_4": {},
    "Icon5_5": {},
    "Icon6": {},
    "Icon7": {},
    "Icon8": {},
    "iconCheck1": {},
    "iconCircle1": {},
    "Image2": {},
    "Image3": {},
    "Label1": {},
    "Label10": {},
    "Label2": {},
    "Label2_1": {},
    "Label2_2": {},
    "Label2_3": {},
    "Label2_4": {},
    "Label2_5": {},
    "Label2_6": {},
    "Label3": {},
    "Label4": {},
    "Label5": {},
    "Label6": {},
    "Label7": {},
    "Label8": {},
    "Label9": {},
    "Last B Check at HMR_DataCard1": {},
    "LblSuccessMsg1": {},
    "Lube Pressure_DataCard1": {},
    "Lube Temp_DataCard1": {},
    "Main Color": {},
    "Menu Screen": {},
    "Mode of Transport_DataCard1": {},
    "NEW_ASSET_LIST": {},
    "NextArrow2": {},
    "NextArrow3": {},
    "OEM (Make)_DataCard1": {},
    "PenInput1": {},
    "Primary Color": {},
    "Priority_Column1": {},
    "Priority_DataCard2": {},
    "Product_Column1": {},
    "Rectangle1": {},
    "Rectangle1_1": {},
    "Rectangle1_2": {},
    "Rectangle1_3": {},
    "Rectangle1_4": {},
    "Rectangle1_5": {},
    "Rectangle1_6": {},
    "Rectangle2": {},
    "Remarks_Column1": {},
    "Remarks_DataCard1": {},
    "secondary Color": {},
    "Separator2": {},
    "Separator3": {},
    "Service Breakdown Type_DataCard1": {},
    "Service Creation": {},
    "Service list": {},
    "Service Representative Name_DataCard1": {},
    "Service Request Action_DataCard1": {},
    "Service Request Type_DataCard1": {},
    "SR Date_DataCard1": {},
    "SR Date_DataCard3": {},
    "SR Status_Column1": {},
    "StarVisible1": {},
    "StarVisible10": {},
    "StarVisible11": {},
    "StarVisible12": {},
    "StarVisible13": {},
    "StarVisible14": {},
    "StarVisible15": {},
    "StarVisible16": {},
    "StarVisible17": {},
    "StarVisible18": {},
    "StarVisible19": {},
    "StarVisible2": {},
    "StarVisible20": {},
    "StarVisible21": {},
    "StarVisible22": {},
    "StarVisible23": {},
    "StarVisible24": {},
    "StarVisible25": {},
    "StarVisible26": {},
    "StarVisible27": {},
    "StarVisible28": {},
    "StarVisible29": {},
    "StarVisible3": {},
    "StarVisible30": {},
    "StarVisible31": {},
    "StarVisible32": {},
    "StarVisible33": {},
    "StarVisible34": {},
    "StarVisible35": {},
    "StarVisible36": {},
    "StarVisible37": {},
    "StarVisible38": {},
    "StarVisible39": {},
    "StarVisible4": {},
    "StarVisible40": {},
    "StarVisible41": {},
    "StarVisible42": {},
    "StarVisible43": {},
    "StarVisible44": {},
    "StarVisible45": {},
    "StarVisible46": {},
    "StarVisible47": {},
    "StarVisible48": {},
    "StarVisible49": {},
    "StarVisible5": {},
    "StarVisible50": {},
    "StarVisible52": {},
    "StarVisible53": {},
    "StarVisible55": {},
    "StarVisible56": {},
    "StarVisible57": {},
    "StarVisible58": {},
    "StarVisible6": {},
    "StarVisible60": {},
    "StarVisible61": {},
    "StarVisible7": {},
    "StarVisible75": {},
    "StarVisible76": {},
    "StarVisible77": {},
    "StarVisible78": {},
    "StarVisible79": {},
    "StarVisible8": {},
    "StarVisible9": {},
    "Status_DataCard1": {},
    "Subtitle2": {},
    "Subtitle3": {},
    "Subtitle3_1": {},
    "Subtitle3_2": {},
    "Subtitle3_3": {},
    "SUCCESS_SCREEN": {},
    "TextInput1": {},
    "TextInput1_1": {},
    "TextInput2": {},
    "TextInput2_1": {},
    "TextInput3": {},
    "Third Color": {},
    "Title_Column1": {},
    "Title_DataCard1": {},
    "Title_DataCard3": {},
    "Title2": {},
    "Title3": {},
    "Type of Coolant_DataCard1": {},
    "VIEW_ASSET_LIST": {},
    "Water Temp_DataCard1": {}
  },
  "PCFDynamicSchemaForIRRetrievalEntry": {},
  "PublishOrderIndices": {
    "Activity initiated_Column1": 461,
    "ALT MODEL_DataCard1": 320,
    "ALT MODEL_DataCard2": 53,
    "ALTERNATOR MAKE_DataCard1": 316,
    "ALTERNATOR MAKE_DataCard2": 49,
    "ALTERNATOR S.NO:_DataCard1": 317,
    "ALTERNATOR S.NO:_DataCard2": 50,
    "App": 0,
    "Asset List": 2,
    "Assigned To_Column1": 459,
    "Attended Date_DataCard1": 85,
    "Body1": 283,
    "Border Color Palatte": 0,
    "Brand and Grade of Lube oil_DataCard1": 212,
    "Breakdown Issues_DataCard1": 137,
    "Button1": 293,
    "Button2": 290,
    "Button3": 359,
    "Button3_10": 157,
    "Button3_11": 156,
    "Button3_12": 200,
    "Button3_13": 199,
    "Button3_6": 124,
    "Button3_7": 123,
    "Button3_8": 268,
    "Button3_9": 267,
    "Button4": 134,
    "Button6": 302,
    "Button6_1": 303,
    "Button6_2": 301,
    "Button6_3": 304,
    "Button6_4": 300,
    "Button6_5": 299,
    "Button7": 45,
    "Call Log Date_Column1": 446,
    "Call Log Type_Column1": 455,
    "Capacity(Kva)_DataCard1": 369,
    "CAPACITY_DataCard1": 318,
    "CAPACITY_DataCard2": 51,
    "ComboBox1": 89,
    "ComboBox2": 275,
    "ComboBox3": 390,
    "ComboBox4": 477,
    "ComboBox5": 476,
    "Complaint_DataCard2": 370,
    "Contact Person Designation_DataCard1": 84,
    "Contact Person Email ID_DataCard1": 83,
    "Contact Person Mobile No_DataCard1": 82,
    "Contact Person Name_DataCard1": 81,
    "Contract Person_Column1": 462,
    "Contract Person_DataCard1": 374,
    "Controller Type_DataCard1": 207,
    "Cumulative Hours_DataCard1": 210,
    "Cust Email Id_DataCard1": 17,
    "Cust Phone Number_DataCard1": 18,
    "Customer Address_DataCard1": 16,
    "Customer City_DataCard1": 15,
    "Customer Company Name_Column1": 449,
    "Customer Company Name_DataCard1": 77,
    "Customer Company Name_DataCard2": 364,
    "Customer Location_Column1": 450,
    "Customer Location_DataCard1": 80,
    "Customer Location_DataCard3": 365,
    "Customer Mail Id_Column1": 458,
    "Customer Name_DataCard1": 14,
    "Customer Number_Column1": 451,
    "Customer Number_DataCard2": 366,
    "DataCard1": 214,
    "DataCard2": 139,
    "DataCard3": 166,
    "DataCard4": 86,
    "DataCard5": 20,
    "DataCard6": 321,
    "DataCardKey1": 92,
    "DataCardKey10": 220,
    "DataCardKey11": 232,
    "DataCardKey12": 236,
    "DataCardKey13": 240,
    "DataCardKey14": 244,
    "DataCardKey15": 248,
    "DataCardKey16": 252,
    "DataCardKey17": 256,
    "DataCardKey18": 260,
    "DataCardKey19": 264,
    "DataCardKey2": 96,
    "DataCardKey20": 216,
    "DataCardKey21": 112,
    "DataCardKey22": 141,
    "DataCardKey23": 145,
    "DataCardKey24": 149,
    "DataCardKey25": 153,
    "DataCardKey26": 168,
    "DataCardKey27": 172,
    "DataCardKey28": 176,
    "DataCardKey29": 180,
    "DataCardKey3": 88,
    "DataCardKey30": 184,
    "DataCardKey31": 188,
    "DataCardKey32": 192,
    "DataCardKey33": 196,
    "DataCardKey34": 104,
    "DataCardKey35": 430,
    "DataCardKey36": 414,
    "DataCardKey37": 410,
    "DataCardKey38": 385,
    "DataCardKey39": 422,
    "DataCardKey4": 100,
    "DataCardKey40": 434,
    "DataCardKey41": 323,
    "DataCardKey42": 327,
    "DataCardKey43": 331,
    "DataCardKey44": 335,
    "DataCardKey45": 339,
    "DataCardKey46": 343,
    "DataCardKey47": 347,
    "DataCardKey48": 351,
    "DataCardKey49": 54,
    "DataCardKey5": 120,
    "DataCardKey50": 56,
    "DataCardKey51": 58,
    "DataCardKey52": 376,
    "DataCardKey53": 381,
    "DataCardKey54": 43,
    "DataCardKey55": 398,
    "DataCardKey56": 402,
    "DataCardKey57": 418,
    "DataCardKey58": 426,
    "DataCardKey59": 393,
    "DataCardKey6": 228,
    "DataCardKey60": 389,
    "DataCardKey61": 406,
    "DataCardKey62": 60,
    "DataCardKey63": 62,
    "DataCardKey64": 64,
    "DataCardKey65": 66,
    "DataCardKey66": 68,
    "DataCardKey7": 116,
    "DataCardKey75": 23,
    "DataCardKey76": 31,
    "DataCardKey77": 35,
    "DataCardKey78": 38,
    "DataCardKey79": 27,
    "DataCardKey8": 108,
    "DataCardKey9": 224,
    "DataCardValue1": 93,
    "DataCardValue10": 221,
    "DataCardValue11": 233,
    "DataCardValue12": 237,
    "DataCardValue13": 241,
    "DataCardValue14": 245,
    "DataCardValue15": 249,
    "DataCardValue16": 253,
    "DataCardValue17": 257,
    "DataCardValue18": 261,
    "DataCardValue19": 265,
    "DataCardValue2": 97,
    "DataCardValue20": 217,
    "DataCardValue21": 113,
    "DataCardValue22": 142,
    "DataCardValue23": 146,
    "DataCardValue24": 150,
    "DataCardValue25": 154,
    "DataCardValue26": 169,
    "DataCardValue27": 173,
    "DataCardValue28": 177,
    "DataCardValue29": 181,
    "DataCardValue3": 121,
    "DataCardValue30": 185,
    "DataCardValue31": 189,
    "DataCardValue32": 193,
    "DataCardValue33": 431,
    "DataCardValue34": 415,
    "DataCardValue35": 411,
    "DataCardValue36": 386,
    "DataCardValue37": 423,
    "DataCardValue38": 435,
    "DataCardValue39": 324,
    "DataCardValue4": 101,
    "DataCardValue40": 328,
    "DataCardValue41": 332,
    "DataCardValue42": 336,
    "DataCardValue43": 340,
    "DataCardValue44": 344,
    "DataCardValue45": 348,
    "DataCardValue46": 352,
    "DataCardValue47": 55,
    "DataCardValue48": 57,
    "DataCardValue49": 59,
    "DataCardValue5": 105,
    "DataCardValue50": 61,
    "DataCardValue51": 378,
    "DataCardValue52": 382,
    "DataCardValue53": 41,
    "DataCardValue54": 399,
    "DataCardValue55": 403,
    "DataCardValue56": 419,
    "DataCardValue57": 427,
    "DataCardValue58": 394,
    "DataCardValue59": 391,
    "DataCardValue6": 117,
    "DataCardValue60": 407,
    "DataCardValue61": 63,
    "DataCardValue62": 65,
    "DataCardValue63": 67,
    "DataCardValue64": 69,
    "DataCardValue7": 109,
    "DataCardValue73": 21,
    "DataCardValue74": 29,
    "DataCardValue75": 33,
    "DataCardValue76": 39,
    "DataCardValue77": 25,
    "DataCardValue8": 229,
    "DataCardValue9": 225,
    "DataTable1": 444,
    "Description of Work Done_DataCard1": 138,
    "DG Set_DataCard1": 206,
    "Digital Signature_DataCard1": 165,
    "Dropdown1": 442,
    "EDIT_ASSET_LIST": 4,
    "ENG MODEL_DataCard1": 319,
    "ENG MODEL_DataCard2": 52,
    "ENGINE MAKE_DataCard1": 314,
    "ENGINE MAKE_DataCard2": 47,
    "Engine Model_DataCard1": 202,
    "Engine No_Column1": 453,
    "Engine No_DataCard1": 368,
    "Engine Serial No_DataCard2": 201,
    "ENGINE SR.NO:_DataCard1": 315,
    "ENGINE SR.NO:_DataCard2": 48,
    "EQMNT NO:_DataCard1": 313,
    "EQMNT NO:_DataCard2": 46,
    "Eqmnt No_Column1": 448,
    "Equipment Name_Column1": 452,
    "Equipment Name_DataCard1": 367,
    "Equipment No_DataCard1": 203,
    "Equipment Type_Column1": 447,
    "Equipment Type_DataCard1": 204,
    "Equipment Type_DataCard2": 362,
    "ErrorMessage1": 94,
    "ErrorMessage10": 222,
    "ErrorMessage11": 234,
    "ErrorMessage12": 238,
    "ErrorMessage13": 242,
    "ErrorMessage14": 246,
    "ErrorMessage15": 250,
    "ErrorMessage16": 254,
    "ErrorMessage17": 258,
    "ErrorMessage18": 262,
    "ErrorMessage19": 266,
    "ErrorMessage2": 98,
    "ErrorMessage20": 218,
    "ErrorMessage21": 114,
    "ErrorMessage22": 143,
    "ErrorMessage23": 147,
    "ErrorMessage24": 151,
    "ErrorMessage25": 155,
    "ErrorMessage26": 170,
    "ErrorMessage27": 174,
    "ErrorMessage28": 178,
    "ErrorMessage29": 182,
    "ErrorMessage3": 90,
    "ErrorMessage30": 186,
    "ErrorMessage31": 190,
    "ErrorMessage32": 194,
    "ErrorMessage33": 198,
    "ErrorMessage34": 106,
    "ErrorMessage35": 432,
    "ErrorMessage36": 416,
    "ErrorMessage37": 412,
    "ErrorMessage38": 387,
    "ErrorMessage39": 424,
    "ErrorMessage4": 102,
    "ErrorMessage40": 436,
    "ErrorMessage41": 325,
    "ErrorMessage42": 329,
    "ErrorMessage43": 333,
    "ErrorMessage44": 337,
    "ErrorMessage45": 341,
    "ErrorMessage46": 345,
    "ErrorMessage47": 349,
    "ErrorMessage48": 353,
    "ErrorMessage49": 44,
    "ErrorMessage5": 122,
    "ErrorMessage50": 395,
    "ErrorMessage52": 379,
    "ErrorMessage53": 383,
    "ErrorMessage55": 400,
    "ErrorMessage56": 404,
    "ErrorMessage57": 420,
    "ErrorMessage58": 428,
    "ErrorMessage6": 230,
    "ErrorMessage60": 392,
    "ErrorMessage61": 408,
    "ErrorMessage7": 118,
    "ErrorMessage75": 24,
    "ErrorMessage76": 32,
    "ErrorMessage77": 36,
    "ErrorMessage78": 40,
    "ErrorMessage79": 28,
    "ErrorMessage8": 110,
    "ErrorMessage9": 226,
    "Fab No_DataCard1": 363,
    "Failed at Hours (HMR)_DataCard1": 209,
    "Failed On Date_DataCard1": 208,
    "Form1": 358,
    "Form2": 311,
    "frmAssetDetails": 132,
    "frmEditAssetList": 9,
    "frmIssueDetails": 130,
    "frmPerformanceCheck": 131,
    "frmSrDetails": 75,
    "frmViewAssetList": 12,
    "FSR_FORM_1": 70,
    "FSR_FORM_2": 125,
    "FSR_TRACKER": 269,
    "Full load AMPS_DataCard1": 161,
    "Full load KW_DataCard1": 162,
    "galAssetList": 478,
    "Gallery1": 129,
    "Gallery2": 276,
    "galleryTemplate1": 133,
    "galleryTemplate2": 278,
    "galleryTemplate3": 480,
    "Group1": 76,
    "Group1_1": 277,
    "Group1_2": 479,
    "Group1_3": 13,
    "Group1_4": 305,
    "Group1_5": 312,
    "HOME_SCREEN": 285,
    "Icon1": 464,
    "Icon10": 11,
    "Icon2": 287,
    "Icon3": 291,
    "Icon4": 72,
    "Icon4_1": 127,
    "Icon4_2": 356,
    "Icon4_3": 271,
    "Icon4_4": 470,
    "Icon4_5": 6,
    "Icon4_6": 297,
    "Icon4_7": 308,
    "Icon5": 74,
    "Icon5_1": 357,
    "Icon5_2": 273,
    "Icon5_3": 472,
    "Icon5_4": 8,
    "Icon5_5": 310,
    "Icon6": 473,
    "Icon7": 440,
    "Icon8": 441,
    "iconCheck1": 466,
    "iconCircle1": 465,
    "Image2": 296,
    "Image3": 292,
    "Label1": 355,
    "Label10": 10,
    "Label2": 73,
    "Label2_1": 128,
    "Label2_2": 272,
    "Label2_3": 471,
    "Label2_4": 7,
    "Label2_5": 298,
    "Label2_6": 309,
    "Label3": 377,
    "Label4": 280,
    "Label5": 439,
    "Label6": 443,
    "Label7": 286,
    "Label8": 3,
    "Label9": 484,
    "Last B Check at HMR_DataCard1": 211,
    "LblSuccessMsg1": 467,
    "Lube Pressure_DataCard1": 160,
    "Lube Temp_DataCard1": 159,
    "Main Color": 0,
    "Menu Screen": 294,
    "Mode of Transport_DataCard1": 164,
    "NEW_ASSET_LIST": 306,
    "NextArrow2": 282,
    "NextArrow3": 485,
    "OEM (Make)_DataCard1": 205,
    "PenInput1": 197,
    "Primary Color": 0,
    "Priority_Column1": 457,
    "Priority_DataCard2": 372,
    "Product_Column1": 454,
    "Rectangle1": 71,
    "Rectangle1_1": 126,
    "Rectangle1_2": 270,
    "Rectangle1_3": 469,
    "Rectangle1_4": 5,
    "Rectangle1_5": 295,
    "Rectangle1_6": 307,
    "Rectangle2": 438,
    "Remarks_Column1": 456,
    "Remarks_DataCard1": 371,
    "secondary Color": 0,
    "Separator2": 284,
    "Separator3": 488,
    "Service Breakdown Type_DataCard1": 136,
    "Service Creation": 354,
    "Service list": 437,
    "Service Representative Name_DataCard1": 163,
    "Service Request Action_DataCard1": 373,
    "Service Request Type_DataCard1": 135,
    "SR Date_DataCard1": 79,
    "SR Date_DataCard3": 361,
    "SR Status_Column1": 460,
    "StarVisible1": 91,
    "StarVisible10": 219,
    "StarVisible11": 231,
    "StarVisible12": 235,
    "StarVisible13": 239,
    "StarVisible14": 243,
    "StarVisible15": 247,
    "StarVisible16": 251,
    "StarVisible17": 255,
    "StarVisible18": 259,
    "StarVisible19": 263,
    "StarVisible2": 95,
    "StarVisible20": 215,
    "StarVisible21": 111,
    "StarVisible22": 140,
    "StarVisible23": 144,
    "StarVisible24": 148,
    "StarVisible25": 152,
    "StarVisible26": 167,
    "StarVisible27": 171,
    "StarVisible28": 175,
    "StarVisible29": 179,
    "StarVisible3": 87,
    "StarVisible30": 183,
    "StarVisible31": 187,
    "StarVisible32": 191,
    "StarVisible33": 195,
    "StarVisible34": 103,
    "StarVisible35": 429,
    "StarVisible36": 413,
    "StarVisible37": 409,
    "StarVisible38": 384,
    "StarVisible39": 421,
    "StarVisible4": 99,
    "StarVisible40": 433,
    "StarVisible41": 322,
    "StarVisible42": 326,
    "StarVisible43": 330,
    "StarVisible44": 334,
    "StarVisible45": 338,
    "StarVisible46": 342,
    "StarVisible47": 346,
    "StarVisible48": 350,
    "StarVisible49": 42,
    "StarVisible5": 119,
    "StarVisible50": 396,
    "StarVisible52": 375,
    "StarVisible53": 380,
    "StarVisible55": 397,
    "StarVisible56": 401,
    "StarVisible57": 417,
    "StarVisible58": 425,
    "StarVisible6": 227,
    "StarVisible60": 388,
    "StarVisible61": 405,
    "StarVisible7": 115,
    "StarVisible75": 22,
    "StarVisible76": 30,
    "StarVisible77": 34,
    "StarVisible78": 37,
    "StarVisible79": 26,
    "StarVisible8": 107,
    "StarVisible9": 223,
    "Status_DataCard1": 19,
    "Subtitle2": 281,
    "Subtitle3": 482,
    "Subtitle3_1": 486,
    "Subtitle3_2": 483,
    "Subtitle3_3": 487,
    "SUCCESS_SCREEN": 463,
    "TextInput1": 288,
    "TextInput1_1": 289,
    "TextInput2": 474,
    "TextInput2_1": 475,
    "TextInput3": 274,
    "Third Color": 0,
    "Title_Column1": 445,
    "Title_DataCard1": 78,
    "Title_DataCard3": 360,
    "Title2": 279,
    "Title3": 481,
    "Type of Coolant_DataCard1": 213,
    "VIEW_ASSET_LIST": 468,
    "Water Temp_DataCard1": 158
  },
  "ResourcesJsonIndices": {
    "Image-997194": 1,
    "Image-App1": 2,
    "Image-App2": 3,
    "Image-App4": 4,
    "Image-App8": 5,
    "Image-background": 6,
    "Image-Home Screen Image": 7,
    "Image-Login": 8,
    "Image-Logout": 9,
    "Image-SampleImage": 0,
    "Image-Service Request": 10,
    "Image-Submit": 11,
    "Image-Technology-modern-abstract-background-vector": 12,
    "Image-white-gradient-blue-linear-1536x2048-c2-87cefa-ffffff-a-90-f-14": 13
  },
  "RuleScreenIdWithoutScreen": {},
  "TemplateVersions": {},
  "VolatileProperties": {
    "AnalysisLoadTime": 5.4724269,
    "ControlCount": {
      "button": 19,
      "circle": 1,
      "combobox": 18,
      "dataTable": 1,
      "dataTableColumn": 18,
      "datepicker": 3,
      "dropdown": 1,
      "form": 8,
      "gallery": 3,
      "galleryTemplate": 3,
      "group": 6,
      "icon": 24,
      "image": 2,
      "inkControl": 1,
      "label": 222,
      "rectangle": 13,
      "screen": 12,
      "text": 58,
      "typedDataCard": 77
    },
    "DeserializationLoadTime": 5.6971658,
    "ErrorCount": 1
  },
  "WasLocalDatabaseReferencesEmpty": true
}